matrixb/__init__.py
matrixb/columnnormalizer.py
matrixb/cube.py
matrixb/iterator.py
matrixb/matrix.py
matrixb/rowmap.py
matrixb/source/__init__.py
matrixb/source/base.py
matrixb/source/csv.py
matrixb/source/googlesheet.py
matrixb/source/resident.py
matrixb/source/xls.py
matrixb/source/xlsx.py
matrixb-0.0.2.0.dist-info/LICENSE.txt
matrixb-0.0.2.0.dist-info/METADATA
matrixb-0.0.2.0.dist-info/WHEEL
matrixb-0.0.2.0.dist-info/top_level.txt
matrixb-0.0.2.0.dist-info/RECORD
