Metadata-Version: 2.1
Name: matrixb
Version: 0.0.2.0
Summary: An extensible package to automate and enhance the manipulation of tabular/matrix data without giving up performance.
Home-page: https://gitlab.com/krcrouse/matrixb
Author: Kevin Crouse
Author-email: krcrouse@gmail.com
License: UNKNOWN
Platform: UNKNOWN
Classifier: Programming Language :: Python :: 3.7
Classifier: License :: OSI Approved :: Apache Software License
Classifier: Operating System :: OS Independent
Classifier: Development Status :: 3 - Alpha
Requires-Dist: openpyxl
Requires-Dist: pydatacleaner
Requires-Dist: python-dateutil
Requires-Dist: xlrd
Requires-Dist: xlwt
Provides-Extra: dataframe
Requires-Dist: pandas ; extra == 'dataframe'
Provides-Extra: source.googlesheet
Requires-Dist: pygoogleapps ; extra == 'source.googlesheet'
Provides-Extra: source.ods
Requires-Dist: pyexcel ; extra == 'source.ods'
Requires-Dist: pyexcel-ods3 ; extra == 'source.ods'
